auto_preprocess/__init__.py
auto_preprocess/data_preprocess.py
pyProcessAutom-1.4.9.dist-info/METADATA
pyProcessAutom-1.4.9.dist-info/WHEEL
pyProcessAutom-1.4.9.dist-info/top_level.txt
pyProcessAutom-1.4.9.dist-info/RECORD
