Metadata-Version: 2.1
Name: pyProcessAutom
Version: 1.4.9
Summary: A data preprocessing library
Home-page: UNKNOWN
Author: Aryan Sakhala
License: UNKNOWN
Platform: UNKNOWN
Requires-Dist: pandas
Requires-Dist: scikit-learn
